opengpt/config.py
opengpt/data_collator.py
opengpt/dataset_utils.py
opengpt/model_utils.py
opengpt/parsers.py
opengpt/prompt_utils.py
opengpt/teachers.py
opengpt-0.0.5.dist-info/LICENSE
opengpt-0.0.5.dist-info/METADATA
opengpt-0.0.5.dist-info/WHEEL
opengpt-0.0.5.dist-info/top_level.txt
opengpt-0.0.5.dist-info/RECORD
