Metadata-Version: 2.1
Name: opengpt
Version: 0.0.5
Summary: OpenGPT a framework for producing grounded domain specific LLMs, and NHS-LLM a conversational model for healthcare made using OpenGPT.
Home-page: https://github.com/cogstack/opengpt
Author: w-is-h
Author-email: w.kraljevic@gmail.com
Classifier: Programming Language :: Python :: 3
Classifier: License :: OSI Approved :: MIT License
Classifier: Operating System :: OS Independent
License-File: LICENSE
Requires-Dist: datasets (<3,>=2)
Requires-Dist: transformers (<5,>=4.2)
Requires-Dist: tiktoken (>=0.3.2)
Requires-Dist: pandas
Requires-Dist: openai
Requires-Dist: numpy
Requires-Dist: tqdm
Requires-Dist: python-box
Requires-Dist: jsonpickle
